PyKhana/__init__.py
PyKhana/pyk.py
PyKhana-0.0.3.dist-info/LICENSE.txt
PyKhana-0.0.3.dist-info/METADATA
PyKhana-0.0.3.dist-info/WHEEL
PyKhana-0.0.3.dist-info/top_level.txt
PyKhana-0.0.3.dist-info/RECORD
