Metadata-Version: 2.1
Name: PyKhana
Version: 0.0.3
Summary: An demonstration of how to implement Gaussian Integer operations in Python.
Home-page: https://github.com/dipampaul17/PyKhana
Author: Dipam Paul
Author-email: dipampaul17@gmail.com
License: MIT
Keywords: PyKhana,GaussianInt
Platform: UNKNOWN
Classifier: Programming Language :: Python :: 3
Classifier: License :: OSI Approved :: MIT License
Classifier: Operating System :: OS Independent
Requires-Python: >=3.6
